Metadata-Version: 1.1
Name: python-baseconv
Version: 1.1.2
Summary: Convert numbers from base 10 integers to base X strings and back again.
Home-page: https://bitbucket.org/semente/baseconv/
Author: Guilherme Gondim
Author-email: semente+baseconv@taurinus.org
License: Python Software Foundation License
Download-URL: https://bitbucket.org/semente/baseconv/downloads/
Keywords: converter numbers math
Platform: UNKNOWN
Classifier: Development Status :: 5 - Production/Stable
Classifier: Intended Audience :: Developers
Classifier: License :: OSI Approved :: Python Software Foundation License
Classifier: Operating System :: OS Independent
Classifier: Programming Language :: Python
Classifier: Topic :: Software Development :: Libraries :: Python Modules
